README.md
setup.py
embarcaderomindmachine/GithubKeymaker.py
embarcaderomindmachine/GithubKeymaker_bmm.py
embarcaderomindmachine/GithubSheep.py
embarcaderomindmachine/GithubShepherd.py
embarcaderomindmachine/__init__.py
embarcaderomindmachine/utils.py
embarcaderomindmachine.egg-info/PKG-INFO
embarcaderomindmachine.egg-info/SOURCES.txt
embarcaderomindmachine.egg-info/dependency_links.txt
embarcaderomindmachine.egg-info/not-zip-safe
embarcaderomindmachine.egg-info/requires.txt
embarcaderomindmachine.egg-info/top_level.txt