Metadata-Version: 1.0
Name: embarcaderomindmachine
Version: 23
Summary: The extensible framework for running Github bot flocks.
Home-page: https://pages.charlesreid1.com/embarcadero-mind-machine
Author: charlesreid1
Author-email: embarcadero@charlesreid1.com
License: MIT
Platform: UNKNOWN
